SSD/__init__.py
SSD/cli.py
SSD/Core/__init__.py
SSD/Core/Rendering/__init__.py
SSD/Core/Rendering/replay.py
SSD/Core/Rendering/user_api.py
SSD/Core/Rendering/visualizer.py
SSD/Core/Rendering/backend/__init__.py
SSD/Core/Rendering/backend/base_object.py
SSD/Core/Rendering/backend/base_replay.py
SSD/Core/Rendering/backend/base_visualizer.py
SSD/Core/Rendering/backend/rendering_table.py
SSD/Core/Rendering/backend/open3d/__init__.py
SSD/Core/Rendering/backend/open3d/open3d_app.py
SSD/Core/Rendering/backend/open3d/open3d_object.py
SSD/Core/Rendering/backend/open3d/open3d_replay.py
SSD/Core/Rendering/backend/open3d/open3d_visualizer.py
SSD/Core/Rendering/backend/open3d/utils.py
SSD/Core/Rendering/backend/vedo/__init__.py
SSD/Core/Rendering/backend/vedo/utils.py
SSD/Core/Rendering/backend/vedo/vedo_objet.py
SSD/Core/Rendering/backend/vedo/vedo_replay.py
SSD/Core/Rendering/backend/vedo/vedo_visualizer.py
SSD/Core/Storage/__init__.py
SSD/Core/Storage/adaptive_table.py
SSD/Core/Storage/database.py
SSD/Core/Storage/exporter.py
SSD/Core/Storage/numpy_field.py
SSD/Core/Storage/peewee_extension.py
SSD/Core/Storage/utils.py
SSD/SOFA/__init__.py
SSD/SOFA/utils.py
SSD/SOFA/Rendering/__init__.py
SSD/SOFA/Rendering/replay.py
SSD/SOFA/Rendering/user_api.py
SSD/SOFA/Rendering/visualizer.py
SSD/SOFA/Storage/__init__.py
SSD/SOFA/Storage/database.py
SSD/examples/Core/rendering/armadillo.obj
SSD/examples/Core/rendering/offscreen.py
SSD/examples/Core/rendering/replay.py
SSD/examples/Core/rendering/several_factories.py
SSD/examples/Core/rendering/several_factories_offscreen.py
SSD/examples/Core/rendering/visualization.py
SSD/examples/Core/storage/foreignkey_db.py
SSD/examples/Core/storage/read_db.py
SSD/examples/Core/storage/signal_db.py
SSD/examples/Core/storage/update_db.py
SSD/examples/Core/storage/utils_db.py
SSD/examples/Core/storage/write_db.py
SSD/examples/SOFA/rendering/Liver.py
SSD/examples/SOFA/rendering/record.py
SSD/examples/SOFA/rendering/replay.py
SimulationSimpleDatabase-24.1.dist-info/LICENSE
SimulationSimpleDatabase-24.1.dist-info/METADATA
SimulationSimpleDatabase-24.1.dist-info/WHEEL
SimulationSimpleDatabase-24.1.dist-info/entry_points.txt
SimulationSimpleDatabase-24.1.dist-info/top_level.txt
SimulationSimpleDatabase-24.1.dist-info/RECORD
