Metadata-Version: 2.1
Name: SimulationSimpleDatabase
Version: 24.1
Summary: A simplified API to use SQL Databases with numerical simulation.
Home-page: https://github.com/RobinEnjalbert/SimulationSimpleDatabase
Author: R. Enjalbert, A. Odot
Author-email: robin.enjalbert@inria.fr
License-File: LICENSE
Requires-Dist: numpy >=1.26.4
Requires-Dist: peewee >=3.17.0
Requires-Dist: vedo >=2024.5.1
Requires-Dist: matplotlib >=3.8.3
Requires-Dist: open3d >=0.16.0
